mpsqd/__init__.py
mpsqd/models/__init__.py
mpsqd/models/construct_holstein.py
mpsqd/models/construct_sb.py
mpsqd/models/init_rho.py
mpsqd/models/models.py
mpsqd/models/construct_tds/__init__.py
mpsqd/models/construct_tds/construct.py
mpsqd/models/construct_tds/construct_simple.py
mpsqd/models/construct_tds/construct_term.py
mpsqd/models/construct_tds/model_define.py
mpsqd/models/construct_tds/model_mctdh.py
mpsqd/models/construct_tds/params_tds.py
mpsqd/models/construct_tds/write_file.py
mpsqd/models/setupfreqs/__init__.py
mpsqd/models/setupfreqs/setupfreqs_debye.py
mpsqd/rk4/__init__.py
mpsqd/rk4/rk4.py
mpsqd/tdvp/__init__.py
mpsqd/tdvp/tdvp.py
mpsqd/tdvp/ttfunc.py
mpsqd/utils/__init__.py
mpsqd/utils/add_tensor.py
mpsqd/utils/mpsdef.py
mpsqd/utils/prod_tensor.py
mpsqd/utils/read_write_mpo.py
mpsqd/utils/split.py
mpsqd/utils/trun.py
mpsqd-0.1.4.dist-info/LICENSE
mpsqd-0.1.4.dist-info/METADATA
mpsqd-0.1.4.dist-info/WHEEL
mpsqd-0.1.4.dist-info/top_level.txt
mpsqd-0.1.4.dist-info/RECORD
